HDL/source/gc_dv_decode.vhd
-- file: gc_dv_decode.vhd

library ieee;
use ieee.std_logic_1164.all;
use ieee.numeric_std.all;

entity gc_dv_decode is
	port(
		vclk	: in	std_logic;
		vphase	: in	std_logic;
		vdata	: in	std_logic_vector(7 downto 0);
		pclk	: out	std_logic;
		Y		: out	std_logic_vector(7 downto 0);
		CbCr	: out	std_logic_vector(7 downto 0);
		is_Cr	: out	std_logic;
		is_odd	: out	std_logic;
		H_sync	: out	std_logic;
		V_sync	: out	std_logic;
		C_sync	: out	std_logic;
		Blanking: out	std_logic;
		dvalid	: out	std_logic
	);
end entity;

architecture behav of gc_dv_decode is
    -- State machine state definition
    type state_slow_typ is (reset, get_vphase_sync, get_Y, get_Y_x2, get_CbCr, get_CbCr_x2);
    signal state_slow               : state_slow_typ := reset;
    type state_fast_typ is (reset, get_vphase_sync, get_Y, get_CbCr);
    signal state_fast               : state_fast_typ := reset;
    
    -- Sample stores
	signal previous_vphase          : std_logic;
	signal vphase_slow_validated    : std_logic;
	signal vphase_fast_validated    : std_logic;
    signal Y_slow                   : std_logic_vector(7 downto 0);
    signal Y_slow_validated         : std_logic_vector(7 downto 0);
    signal Y_fast                   : std_logic_vector(7 downto 0);
    signal Y_fast_validated         : std_logic_vector(7 downto 0);
    signal CbCr_slow                : std_logic_vector(7 downto 0);
    signal CbCr_slow_validated      : std_logic_vector(7 downto 0);
    signal CbCr_fast                : std_logic_vector(7 downto 0);
    signal CbCr_fast_validated      : std_logic_vector(7 downto 0);
    signal dvalid_slow              : std_logic := '0';
    signal dinvalid_slow            : std_logic := '0';
    signal dvalid_fast              : std_logic := '0';
    signal dinvalid_fast            : std_logic := '0';

    -- Active source indication
    type source_typ is (none, slow, fast);
    signal source_active            : source_typ := none;

    -- Pixel clock
    type pclk_state_typ is (pclk_wait, pclk_low_slow, pclk_high_slow, pclk_high_slow_x2, pclk_high_fast);
    signal pclk_state               : pclk_state_typ := pclk_wait;
begin
    -- Store previous vphase state
    vphase_update: process(vclk)
    begin
        if (rising_edge(vclk)) then
            previous_vphase <= vphase;
        end if; -- if (rising_edge(vclk))
    end process;

    -- State machine transitions - vdata format: <Y0><Y0><CbCr0><CbCr0><Y1><Y1><CbCr0><CbCr0>...
    state_update_slow: process(vclk)
    begin
        if (rising_edge(vclk)) then
            -- State machine transitions
            case state_slow is
                when reset =>
                    dvalid_slow <= '0';
                    dinvalid_slow <= '1';
                    Y_slow <= x"00";
                    CbCr_slow <= x"00";
                    state_slow <= get_vphase_sync;
                when get_vphase_sync =>
                    dvalid_slow <= '0';
                    dinvalid_slow <= '1';
                    if (previous_vphase /= vphase) then
                        Y_slow <= vdata;
                        CbCr_slow <= x"00";
                        state_slow <= get_Y_x2;
                    else
                        Y_slow <= x"00";
                        CbCr_slow <= x"00";
                        state_slow <= get_vphase_sync;
                    end if;
                when get_Y =>
                    if (previous_vphase /= vphase) then -- New slow mode samples detected. Set outputs.
                        dvalid_slow <= '1';
                        dinvalid_slow <= '0';
                        vphase_fast_validated <= previous_vphase;
                        Y_slow_validated <= Y_slow;
                        CbCr_slow_validated <= CbCr_slow;
                        Y_slow <= vdata;
                        CbCr_slow <= x"00";
                        state_slow <= get_Y_x2;
                    else -- Reset - a vphase change should have happened.
                        dvalid_slow <= '0';
                        dinvalid_slow <= '1';
                        Y_slow <= x"00";
                        CbCr_slow <= x"00";
                        state_slow <= get_vphase_sync;
                    end if;
                when get_Y_x2 =>
                    dvalid_slow <= '0';
                    dinvalid_slow <= '0';
                    if (previous_vphase = vphase) then
                        Y_slow <= vdata;
                        CbCr_slow <= x"00";
                        state_slow <= get_CbCr;
                    else -- Unexpected start of new cycle. Get Y sample.
                        Y_slow <= vdata;
                        CbCr_slow <= x"00";
                        state_slow <= get_Y_x2;
                    end if;
                when get_CbCr =>
                    dvalid_slow <= '0';
                    dinvalid_slow <= '0';
                    if (previous_vphase = vphase) then
                        Y_slow <= Y_slow;
                        CbCr_slow <= vdata;
                        state_slow <= get_CbCr_x2;
                    else -- Unexpected start of new cycle. Get Y sample.
                        Y_slow <= vdata;
                        CbCr_slow <= x"00";
                        state_slow <= get_Y_x2;
                    end if;
                when get_CbCr_x2 =>
                    dvalid_slow <= '0';
                    dinvalid_slow <= '0';
                    if (previous_vphase = vphase) then
                        Y_slow <= Y_slow;
                        CbCr_slow <= vdata;
                        state_slow <= get_Y;
                    else -- Unexpected start of new cycle. Get Y sample.
                        Y_slow <= vdata;
                        CbCr_slow <= x"00";
                        state_slow <= get_Y_x2;
                    end if;
                when others => state_slow <= get_vphase_sync;
            end case;
        end if; -- if (rising_edge(vclk))
    end process;

    -- State machine transitions - vdata format: <Y0><CbCr0><Y1><CbCr0>...
    state_update_fast: process(vclk)
    begin
        if (rising_edge(vclk)) then
            -- State machine transitions
            case state_fast is
                when reset =>
                    dvalid_fast <= '0';
                    dinvalid_fast <= '1';
                    Y_fast <= x"00";
                    CbCr_fast <= x"00";
                    state_fast <= get_vphase_sync;
                when get_vphase_sync =>
                    dvalid_fast <= '0';
                    dinvalid_fast <= '1';
                    if (previous_vphase /= vphase) then
                        Y_fast <= vdata;
                        CbCr_fast <= x"00";
                        state_fast <= get_CbCr;
                    else
                        Y_fast <= x"00";
                        CbCr_fast <= x"00";
                        state_fast <= get_vphase_sync;
                    end if;
                when get_Y =>
                    if (previous_vphase /= vphase) then -- New fast mode samples detected. Set outputs.
                        dvalid_fast <= '1';
                        dinvalid_fast <= '0';
                        vphase_fast_validated <= previous_vphase;
                        Y_fast_validated <= Y_fast;
                        CbCr_fast_validated <= CbCr_fast;
                        Y_fast <= vdata;
                        CbCr_fast <= x"00";
                        state_fast <= get_CbCr;
                    else -- Reset - a vphase change should have happened.
                        dvalid_fast <= '0';
                        dinvalid_fast <= '1';
                        Y_fast <= x"00";
                        CbCr_fast <= x"00";
                        state_fast <= get_vphase_sync;
                    end if;
                when get_CbCr =>
                    dvalid_fast <= '0';
                    dinvalid_fast <= '0';
                    if (previous_vphase = vphase) then
                        Y_fast <= Y_fast;
                        CbCr_fast <= vdata;
                        state_fast <= get_Y;
                    else -- Unexpected start of new cycle. Get Y sample.
                        Y_fast <= vdata;
                        CbCr_fast <= x"00";
                        state_fast <= get_CbCr;
                    end if;
                when others => state_fast <= get_vphase_sync;
            end case; --case state_fast is
        end if; -- if (rising_edge(vclk))
    end process;

    -- Select output source between slow or fast mode state machines
    source_select: process(vclk)
        variable new_sample             : std_logic;
        variable vphase_sample          : std_logic;
        variable Y_sample               : std_logic_vector(7 downto 0);
        variable CbCr_sample            : std_logic_vector(7 downto 0);
    begin
        if (rising_edge(vclk)) then
            -- Select source of samples
            if (dvalid_slow = '1') then
                new_sample := '1';
                vphase_sample := vphase_slow_validated;
                Y_sample := Y_slow_validated;
                CbCr_sample := CbCr_slow_validated;
            elsif (dvalid_fast = '1') then
                new_sample := '1';
                vphase_sample := vphase_fast_validated;
                Y_sample := Y_fast_validated;
                CbCr_sample := CbCr_fast_validated;
            else
                new_sample := '0';
            end if;

			-- If new sample exists, set output interface video values and flags
			if (new_sample = '1') then
				if (Y_sample = x"00") then	-- blanking data
					Y <= x"10";
					CbCr <= x"80";
					H_sync <= not CbCr_sample(4);	-- Active low.
					V_sync <= not CbCr_sample(5);	-- Active low.
					is_odd <= not CbCr_sample(6);	-- Active low.
					C_sync <= not CbCr_sample(7);	-- Active low.
					Blanking <= '1';
					is_Cr <= '0';
				else						-- video sample
					Y <= Y_sample;
					CbCr <= CbCr_sample;
					H_sync <= '0';
					V_sync <= '0';
					is_odd <= '0';
					C_sync <= '0';
					Blanking <= '0';
					
					if (vphase_sample = '1') then
						is_Cr <= '1';
					else
						is_Cr <= '0';
					end if;	-- if (vphase_sample = '1')
				end if;	-- if (Y_sample = x"00")
			end if;	-- if (new_sample = '1')
        end if; -- if (rising_edge(vclk))
    end process;

    -- Select output data valid flag and generate pixel clock
    dvalid_pclk_update: process(vclk)
    begin
        if (rising_edge(vclk)) then
            -- Set data valid flag and source indication
            if (((dinvalid_slow = '1') and (source_active = slow)) or ((dinvalid_fast = '1') and (source_active = fast))) then 
                source_active <= none;
				dvalid <= '0';
            elsif (dvalid_slow = '1') then
                source_active <= slow;
                dvalid <= '1';
            elsif (dvalid_fast = '1') then
                source_active <= fast;
                dvalid <= '1';
            end if;

            -- Pixel clock generation
            if (((dinvalid_slow = '1') and (source_active = slow)) or ((dinvalid_fast = '1') and (source_active = fast))) then 
                pclk <= '0';
				pclk_state <= pclk_wait;
            elsif (dvalid_slow = '1') then
                pclk <= '0';
                pclk_state <= pclk_low_slow;
            elsif (dvalid_fast = '1') then
                pclk <= '0';
                pclk_state <= pclk_high_fast;
            else
                case pclk_state is
                    when pclk_wait =>
                        pclk <= '0';
                        pclk_state <= pclk_wait;
                    when pclk_low_slow =>
                        pclk <= '0';
                        pclk_state <= pclk_high_slow;
                    when pclk_high_slow =>
                        pclk <= '1';
                        pclk_state <= pclk_high_slow_x2;
                    when pclk_high_slow_x2 =>
                        pclk <= '1';
                        pclk_state <= pclk_wait;
                    when pclk_high_fast =>
                        pclk <= '1';
                        pclk_state <= pclk_wait;
                end case; --case pclk_state is
            end if;
        end if; -- if (rising_edge(vclk))
    end process;
end behav;

HDL/testbench/gc_dv_decode_tb02.vhd
-- file: gc_dv_decode_tb02.vhd

library ieee;
use ieee.std_logic_1164.all;
use ieee.numeric_std.all;

entity gc_dv_decode_tb is
end entity;

architecture behav of gc_dv_decode_tb is

	component gc_dv_decode is
		port(
			vclk	: in	std_logic;
			vphase	: in	std_logic;
			vdata	: in	std_logic_vector(7 downto 0);
			pclk	: out	std_logic;
			Y		: out	std_logic_vector(7 downto 0);
			CbCr	: out	std_logic_vector(7 downto 0);
			is_Cr	: out	std_logic;
			is_odd	: out	std_logic;
			H_sync	: out	std_logic;
			V_sync	: out	std_logic;
			C_sync	: out	std_logic;
			Blanking: out	std_logic;
			dvalid	: out	std_logic
		);
	end component;
	
	-- Test bench signals
	signal vclk_tb		: std_logic;
	signal vphase_tb	: std_logic;
	signal vdata_tb		: std_logic_vector(7 downto 0);
	signal pclk_tb		: std_logic;
	signal Y_tb			: std_logic_vector(7 downto 0);
	signal CbCr_tb		: std_logic_vector(7 downto 0);
	signal is_Cr_tb		: std_logic;
	signal is_odd_tb	: std_logic;
	signal H_sync_tb	: std_logic;
	signal V_sync_tb	: std_logic;
	signal C_sync_tb	: std_logic;
	signal Blanking_tb	: std_logic;
	signal dvalid_tb	: std_logic;
	
	-- Declare record type to build a test vector for this test bench
	type test_vector is record
			vclk_tb		: std_logic;
			vphase_tb	: std_logic;
			vdata_tb	: std_logic_vector(7 downto 0);
	end record;

	type test_vector_array is array (natural range <>) of test_vector;
	constant test_vectors : test_vector_array := (
		-- vclk, vphase, vdata
		  ('0',  '0',    x"00"),	-- slow data, blanking data, raw flags low, invalid number of samples
		  ('1',  '0',    x"00"),
		  ('0',  '0',    x"00"),
		  ('1',  '0',    x"00"),
		  ('0',  '0',    x"00"),
		  ('1',  '0',    x"00"),
		  ('0',  '0',    x"00"),
		  ('1',  '0',    x"00"),
		  
		  ('0',  '1',    x"00"),	-- slow data, blanking data, raw flag bit 4 low (H_sync)
		  ('1',  '1',    x"00"),
		  ('0',  '1',    x"00"),
		  ('1',  '1',    x"00"),
		  ('0',  '1',    x"EF"),
		  ('1',  '1',    x"EF"),
		  ('0',  '1',    x"EF"),
		  ('1',  '1',    x"EF"),
		  
		  ('0',  '0',    x"00"),	-- slow data, blanking data, raw flag bit 5 low (V_sync)
		  ('1',  '0',    x"00"),
		  ('0',  '0',    x"00"),
		  ('1',  '0',    x"00"),
		  ('0',  '0',    x"DF"),
		  ('1',  '0',    x"DF"),
		  ('0',  '0',    x"DF"),
		  ('1',  '0',    x"DF"),
		  
		  ('0',  '1',    x"00"),	-- slow data, blanking data, raw flag bit 7 low (C_sync)
		  ('1',  '1',    x"00"),
		  ('0',  '1',    x"00"),
		  ('1',  '1',    x"00"),
		  ('0',  '1',    x"7F"),
		  ('1',  '1',    x"7F"),
		  ('0',  '1',    x"7F"),
		  ('1',  '1',    x"7F"),
		  
		  ('0',  '0',    x"00"),	-- slow data, blanking data
		  ('1',  '0',    x"00"),
		  ('0',  '0',    x"00"),
		  ('1',  '0',    x"00"),
		  ('0',  '0',    x"FF"),
		  ('1',  '0',    x"FF"),
		  ('0',  '0',    x"FF"),
		  ('1',  '0',    x"FF"),
		  
		  ('0',  '1',    x"01"),
		  ('1',  '1',    x"01"),
		  ('0',  '1',    x"01"),
		  ('1',  '1',    x"01"),
		  ('0',  '1',    x"01"),
		  ('1',  '1',    x"01"),
		  ('0',  '1',    x"01"),
		  ('1',  '1',    x"01"),
		  
		  ('0',  '0',    x"02"),
		  ('1',  '0',    x"02"),
		  ('0',  '0',    x"02"),
		  ('1',  '0',    x"02"),
		  ('0',  '0',    x"02"),
		  ('1',  '0',    x"02"),
		  ('0',  '0',    x"02"),
		  ('1',  '0',    x"02"),
		  
		  ('0',  '1',    x"04"),	-- slow data, invalid number of samples
		  ('1',  '1',    x"04"),
		  ('0',  '1',    x"04"),
		  ('1',  '1',    x"04"),
		  ('0',  '1',    x"04"),
		  ('1',  '1',    x"04"),
		  ('0',  '1',    x"04"),
		  ('1',  '1',    x"04"),
		  ('0',  '1',    x"04"),
		  ('1',  '1',    x"04"),
		  
		  ('0',  '0',    x"08"),
		  ('1',  '0',    x"08"),
		  ('0',  '0',    x"08"),
		  ('1',  '0',    x"08"),
		  ('0',  '0',    x"08"),
		  ('1',  '0',    x"08"),
		  ('0',  '0',    x"08"),
		  ('1',  '0',    x"08"),
		  
		  ('0',  '1',    x"10"),
		  ('1',  '1',    x"10"),
		  ('0',  '1',    x"10"),
		  ('1',  '1',    x"10"),
		  ('0',  '1',    x"10"),
		  ('1',  '1',    x"10"),
		  ('0',  '1',    x"10"),
		  ('1',  '1',    x"10"),
		  
		  ('0',  '0',    x"20"),
		  ('1',  '0',    x"20"),
		  ('0',  '0',    x"20"),
		  ('1',  '0',    x"20"),
		  ('0',  '0',    x"20"),
		  ('1',  '0',    x"20"),
		  ('0',  '0',    x"20"),
		  ('1',  '0',    x"20"),
		  
		  ('0',  '1',    x"40"),
		  ('1',  '1',    x"40"),
		  ('0',  '1',    x"40"),
		  ('1',  '1',    x"40"),
		  ('0',  '1',    x"40"),
		  ('1',  '1',    x"40"),
		  ('0',  '1',    x"40"),
		  ('1',  '1',    x"40"),
		  
		  ('0',  '0',    x"80"),
		  ('1',  '0',    x"80"),
		  ('0',  '0',    x"80"),
		  ('1',  '0',    x"80"),
		  ('0',  '0',    x"80"),
		  ('1',  '0',    x"80"),
		  ('0',  '0',    x"80"),
		  ('1',  '0',    x"80"),
		  
		  ('0',  '1',    x"00"),
		  ('1',  '1',    x"00"),
		  ('0',  '1',    x"00"),
		  ('1',  '1',    x"00"),
		  ('0',  '1',    x"00"),
		  ('1',  '1',    x"00"),
		  ('0',  '1',    x"00"),
		  ('1',  '1',    x"00"),
		  
		  ('0',  '0',    x"00"),
		  ('1',  '0',    x"00"),
		  ('0',  '0',    x"00"),
		  ('1',  '0',    x"00"),
		  ('0',  '0',    x"00"),
		  ('1',  '0',    x"00"),
		  ('0',  '0',    x"00"),
		  ('1',  '0',    x"00")
		);
begin
	
	uut: component gc_dv_decode port map (
		vclk		=> vclk_tb,
		vphase		=> vphase_tb,
		vdata		=> vdata_tb,
		pclk		=> pclk_tb,
		Y			=> Y_tb,
		CbCr		=> CbCr_tb,
		is_Cr		=> is_Cr_tb,
		is_odd		=> is_odd_tb,
		H_sync		=> H_sync_tb,
		V_sync		=> V_sync_tb,
		C_sync		=> C_sync_tb,
		Blanking	=> Blanking_tb,
		dvalid		=> dvalid_tb
	);
	
	tb1 : process
		constant period: time := 20 ns;
	begin
		for i in test_vectors'range loop
			-- Feed in test data from ith test vector line
			vclk_tb <= test_vectors(i).vclk_tb;
			vphase_tb <= test_vectors(i).vphase_tb;
			vdata_tb <= test_vectors(i).vdata_tb;

			wait for period;
		end loop;
		
		wait;
	end process;
end behav;

HDL/simulation/gc_dv_decode_tb03.vcd
$date
  Sun Mar 14 12:19:41 2021
$end
$version
  GHDL v0
$end
$timescale
  1 fs
$end
$scope module standard $end
$upscope $end
$scope module std_logic_1164 $end
$upscope $end
$scope module numeric_std $end
$upscope $end
$scope module gc_dv_decode_tb $end
$var reg 1 ! vclk_tb $end
$var reg 1 " vphase_tb $end
$var reg 8 # vdata_tb[7:0] $end
$var reg 1 $ pclk_tb $end
$var reg 8 % y_tb[7:0] $end
$var reg 8 & cbcr_tb[7:0] $end
$var reg 1 ' is_cr_tb $end
$var reg 1 ( is_odd_tb $end
$var reg 1 ) h_sync_tb $end
$var reg 1 * v_sync_tb $end
$var reg 1 + c_sync_tb $end
$var reg 1 , blanking_tb $end
$var reg 1 - dvalid_tb $end
$scope module uut $end
$var reg 1 . vclk $end
$var reg 1 / vphase $end
$var reg 8 0 vdata[7:0] $end
$var reg 1 1 pclk $end
$var reg 8 2 y[7:0] $end
$var reg 8 3 cbcr[7:0] $end
$var reg 1 4 is_cr $end
$var reg 1 5 is_odd $end
$var reg 1 6 h_sync $end
$var reg 1 7 v_sync $end
$var reg 1 8 c_sync $end
$var reg 1 9 blanking $end
$var reg 1 : dvalid $end
$comment state_slow is not handled $end
$comment state_fast is not handled $end
$var reg 1 ; previous_vphase $end
$var reg 1 < vphase_slow_validated $end
$var reg 1 = vphase_fast_validated $end
$var reg 8 > y_slow[7:0] $end
$var reg 8 ? y_slow_validated[7:0] $end
$var reg 8 @ y_fast[7:0] $end
$var reg 8 A y_fast_validated[7:0] $end
$var reg 8 B cbcr_slow[7:0] $end
$var reg 8 C cbcr_slow_validated[7:0] $end
$var reg 8 D cbcr_fast[7:0] $end
$var reg 8 E cbcr_fast_validated[7:0] $end
$var reg 1 F dvalid_slow $end
$var reg 1 G dinvalid_slow $end
$var reg 1 H dvalid_fast $end
$var reg 1 I dinvalid_fast $end
$comment source_active is not handled $end
$comment pclk_state is not handled $end
$upscope $end
$upscope $end
$enddefinitions $end
#0
0!
0"
b00000000 #
U$
bUUUUUUUU %
bUUUUUUUU &
U'
U(
U)
U*
U+
U,
U-
0.
0/
b00000000 0
U1
bUUUUUUUU 2
bUUUUUUUU 3
U4
U5
U6
U7
U8
U9
U:
U;
U<
U=
bUUUUUUUU >
bUUUUUUUU ?
bUUUUUUUU @
bUUUUUUUU A
bUUUUUUUU B
bUUUUUUUU C
bUUUUUUUU D
bUUUUUUUU E
0F
0G
0H
0I
#20000000
1!
0$
1.
01
0;
b00000000 >
b00000000 @
b00000000 B
b00000000 D
1G
1I
#40000000
0!
0.
#60000000
1!
1.
#80000000
0!
0.
#100000000
1!
1.
#120000000
0!
0.
#140000000
1!
1.
#160000000
0!
1"
0.
1/
#180000000
1!
1.
1;
#200000000
0!
b11101111 #
0.
b11101111 0
#220000000
1!
1.
b11101111 >
b11101111 D
0G
0I
#240000000
0!
0"
b00000000 #
0.
0/
b00000000 0
#260000000
1!
1.
0;
1=
b00000000 >
b00000000 A
b00000000 D
b11101111 E
1H
#280000000
0!
0.
#300000000
1!
b00010000 %
b10000000 &
0'
0(
1)
0*
0+
1,
1-
1.
b00010000 2
b10000000 3
04
05
16
07
08
19
1:
0H
#320000000
0!
b11011111 #
0.
b11011111 0
#340000000
1!
1$
1.
11
b11011111 B
1I
#360000000
0!
0.
#380000000
1!
0$
0-
1.
01
0:
#400000000
0!
1"
b00000000 #
0.
1/
b00000000 0
#420000000
1!
1.
1;
0<
b00000000 ?
b00000000 B
b11011111 C
1F
#440000000
0!
b01111111 #
0.
b01111111 0
#460000000
1!
0)
1*
1-
1.
06
17
1:
b01111111 >
b01111111 D
0F
0I
#480000000
0!
0"
b00000000 #
0.
0/
b00000000 0
#500000000
1!
1.
0;
b00000000 >
b00000000 D
b01111111 E
1H
#520000000
0!
0.
#540000000
1!
0*
1+
1.
07
18
0H
#560000000
0!
b11111111 #
0.
b11111111 0
#580000000
1!
1$
1.
11
b11111111 B
1I
#600000000
0!
0.
#620000000
1!
0$
0-
1.
01
0:
#640000000
0!
1"
b00000001 #
0.
1/
b00000001 0
#660000000
1!
1.
1;
b00000001 >
b00000001 @
b00000000 B
b11111111 C
1F
#680000000
0!
0.
#700000000
1!
0+
1-
1.
08
1:
b00000001 D
0F
0I
#720000000
0!
0"
b00000010 #
0.
0/
b00000010 0
#740000000
1!
1.
0;
b00000010 >
b00000010 @
b00000001 A
b00000000 D
b00000001 E
1H
#760000000
0!
0.
#780000000
1!
b00000001 %
b00000001 &
1'
0,
1.
b00000001 2
b00000001 3
14
09
b00000010 D
0H
#800000000
0!
0.
#820000000
1!
1$
1.
11
b00000000 @
b00000010 B
b00000000 D
1I
#840000000
0!
0.
#860000000
1!
0$
0-
1.
01
0:
#880000000
0!
1"
b00000100 #
0.
1/
b00000100 0
#900000000
1!
1.
1;
b00000100 >
b00000010 ?
b00000100 @
b00000000 B
b00000010 C
1F
#920000000
0!
0.
#940000000
1!
b00000010 %
b00000010 &
0'
1-
1.
b00000010 2
b00000010 3
04
1:
b00000100 D
0F
0I
#960000000
0!
0"
b00001000 #
0.
0/
b00001000 0
#980000000
1!
1.
0;
b00001000 >
b00001000 @
b00000100 A
b00000000 D
b00000100 E
1H
#1000000000
0!
0.
#1020000000
1!
b00000100 %
b00000100 &
1'
1.
b00000100 2
b00000100 3
14
b00001000 D
0H
#1040000000
0!
0.
#1060000000
1!
1$
1.
11
b00000000 @
b00001000 B
b00000000 D
1I
#1080000000
0!
0.
#1100000000
1!
0$
0-
1.
01
0:
#1120000000
0!
1"
b00010000 #
0.
1/
b00010000 0
#1140000000
1!
1.
1;
b00010000 >
b00001000 ?
b00010000 @
b00000000 B
b00001000 C
1F
#1160000000
0!
0.
#1180000000
1!
b00001000 %
b00001000 &
0'
1-
1.
b00001000 2
b00001000 3
04
1:
b00010000 D
0F
0I
#1200000000
0!
0"
b00100000 #
0.
0/
b00100000 0
#1220000000
1!
1.
0;
b00100000 >
b00100000 @
b00010000 A
b00000000 D
b00010000 E
1H
#1240000000
0!
0.
#1260000000
1!
b00010000 %
b00010000 &
1'
1.
b00010000 2
b00010000 3
14
b00100000 D
0H
#1280000000
0!
0.
#1300000000
1!
1$
1.
11
b00000000 @
b00100000 B
b00000000 D
1I
#1320000000
0!
0.
#1340000000
1!
0$
0-
1.
01
0:
#1360000000
0!
1"
b01000000 #
0.
1/
b01000000 0
#1380000000
1!
1.
1;
b01000000 >
b00100000 ?
b01000000 @
b00000000 B
b00100000 C
1F
#1400000000
0!
0.
#1420000000
1!
b00100000 %
b00100000 &
0'
1-
1.
b00100000 2
b00100000 3
04
1:
b01000000 D
0F
0I
#1440000000
0!
0"
b10000000 #
0.
0/
b10000000 0
#1460000000
1!
1.
0;
b10000000 >
b10000000 @
b01000000 A
b00000000 D
b01000000 E
1H
#1480000000
0!
0.
#1500000000
1!
b01000000 %
b01000000 &
1'
1.
b01000000 2
b01000000 3
14
b10000000 D
0H
#1520000000
0!
0.
#1540000000
1!
1$
1.
11
b00000000 @
b10000000 B
b00000000 D
1I
#1560000000
0!
0.
#1580000000
1!
0$
0-
1.
01
0:
#1600000000
0!
1"
b00000000 #
0.
1/
b00000000 0
#1620000000
1!
1.
1;
b00000000 >
b10000000 ?
b00000000 B
b10000000 C
1F
#1640000000
0!
0.
#1660000000
1!
b10000000 %
b10000000 &
0'
1-
1.
b10000000 2
b10000000 3
04
1:
0F
0I
#1680000000
0!
0"
0.
0/
#1700000000
1!
1.
0;
b00000000 A
b00000000 E
1H
#1720000000
0!
0.
#1740000000
1!
b00010000 %
1(
1)
1*
1+
1,
1.
b00010000 2
15
16
17
18
19
0H
#1760000000
0!
0.
#1780000000
1!
1$
1.
11
1I
#1800000000
0!
0.
#1820000000
1!
0$
0-
1.
01
0:
