HDL/source/gc_dv_422_to_444.vhd
-- file: gc_dv_422_to_444.vhd

library ieee;
use ieee.std_logic_1164.all;
use ieee.numeric_std.all;

entity gc_dv_422_to_444 is
	port(
		vclk		: in	std_logic;
		pclk		: in	std_logic;
		Y			: in	std_logic_vector(7 downto 0);
		CbCr		: in	std_logic_vector(7 downto 0);
		is_Cr		: in	std_logic;
		is_odd		: in	std_logic;
		H_sync		: in	std_logic;
		V_sync		: in	std_logic;
		C_sync		: in	std_logic;
		Blanking	: in	std_logic;
		dvalid		: in	std_logic;
		pclk_out	: out	std_logic;
		Y_out		: out	std_logic_vector(7 downto 0);
		Cb_out		: out	std_logic_vector(7 downto 0);
		Cr_out		: out	std_logic_vector(7 downto 0);
		H_sync_out	: out	std_logic;
		V_sync_out	: out	std_logic;
		C_sync_out	: out	std_logic;
		Blanking_out: out	std_logic;
		dvalid_out	: out	std_logic
	);
end entity;

architecture behav of gc_dv_422_to_444 is
	-- Chroma samples
	signal Cb_sample		: std_logic_vector(7 downto 0);
	signal Cr_sample		: std_logic_vector(7 downto 0);
	
	-- Chroma flags
	signal Cb_loaded		: std_logic := '0';
	signal Cr_loaded		: std_logic := '0';
	
	-- Pipes for luma samples and flags
	constant delay_plen		: natural := 2;
	type sample_array_type is array (natural range <>) of std_logic_vector(7 downto 0);
	signal Y_pipe			: sample_array_type(0 to delay_plen - 1);
	type flag_array_type is array (natural range <>) of std_logic;
	signal pclk_pipe		: flag_array_type(0 to delay_plen*2);
	signal H_sync_pipe		: flag_array_type(0 to delay_plen - 1);
	signal V_sync_pipe		: flag_array_type(0 to delay_plen - 1);
	signal C_sync_pipe		: flag_array_type(0 to delay_plen - 1);
	signal Blanking_pipe	: flag_array_type(0 to delay_plen - 1);
	signal dvalid_pipe		: flag_array_type(0 to delay_plen - 1);
	
begin
	duplicate_chroma_samples : process(vclk)
	begin
		if (rising_edge(vclk)) then
			-- Store copy and delay pclk
			if (pclk_pipe(0) /= pclk) then
				-- Delay pixel clock transitions
				pclk_pipe <= pclk & pclk_pipe(0 to delay_plen*2 - 1);
				pclk_out <= pclk_pipe(delay_plen*2);
			end if;

			if ((pclk_pipe(0) = '0') and (pclk = '1')) then
				-- Delay Y sample values and flags
				Y_pipe <= Y & Y_pipe(0 to delay_plen - 2);
				H_sync_pipe <= H_sync & H_sync_pipe(0 to delay_plen - 2);
				V_sync_pipe <= V_sync & V_sync_pipe(0 to delay_plen - 2);
				C_sync_pipe <= C_sync & C_sync_pipe(0 to delay_plen - 2);
				Blanking_pipe <= Blanking & Blanking_pipe(0 to delay_plen - 2);
				dvalid_pipe <= dvalid & dvalid_pipe(0 to delay_plen - 2);
	
				-- Copy delayed samples to output
				Y_out <= Y_pipe(delay_plen - 1);
				H_sync_out <= H_sync_pipe(delay_plen - 1);
				V_sync_out <= V_sync_pipe(delay_plen - 1);
				C_sync_out <= C_sync_pipe(delay_plen - 1);
				Blanking_out <= Blanking_pipe(delay_plen - 1);
				dvalid_out <= dvalid_pipe(delay_plen - 1);
				
				-- When both Cr and Cb samples are stored, shift them to output.
				if ((Cr_loaded = '1') and (Cb_loaded = '1')) then
					Cr_out <= Cr_sample;
					Cb_out <= Cb_sample;
					Cr_loaded <= '0';
					Cb_loaded <= '0';
				end if; -- if ((Cr_loaded = '1') and (Cb_loaded = '1'))
				
				-- Separate Cb and Cr sample values.
				if (is_Cr = '1') then
					Cr_sample <= CbCr;
					Cr_loaded <= '1';
				else
					Cb_sample <= CbCr;
					Cb_loaded <= '1';
				end if; -- if (is_Cr = '1')
				
				-- If incoming data is in blanking state, set defaults
				if (Blanking = '1') then
					Cr_sample <= CbCr;
					Cb_sample <= CbCr;
					Cr_loaded <= '1';
					Cb_loaded <= '1';
				end if; -- if (Blanking = '1')
			end if; -- if ((pclk_pipe(0) = '0') and (pclk = '1'))
		end if;	-- if (rising_edge(vclk))
	end process; -- duplicate_chroma_samples : process(pclk)
end behav;

HDL/testbench/gc_dv_422_to_444_tb01.vhd
-- file: gc_dv_422_to_444_tb.vhd

library ieee;
use ieee.std_logic_1164.all;
use ieee.numeric_std.all;

entity gc_dv_422_to_444_tb is
end entity;

architecture behav of gc_dv_422_to_444_tb is
	component gc_dv_422_to_444 is
		port(
			vclk		: in	std_logic;
			pclk		: in	std_logic;
			Y			: in	std_logic_vector(7 downto 0);
			CbCr		: in	std_logic_vector(7 downto 0);
			is_Cr		: in	std_logic;
			is_odd		: in	std_logic;
			H_sync		: in	std_logic;
			V_sync		: in	std_logic;
			C_sync		: in	std_logic;
			Blanking	: in	std_logic;
			dvalid		: in	std_logic;
			pclk_out	: out	std_logic;
			Y_out		: out	std_logic_vector(7 downto 0);
			Cb_out		: out	std_logic_vector(7 downto 0);
			Cr_out		: out	std_logic_vector(7 downto 0);
			H_sync_out	: out	std_logic;
			V_sync_out	: out	std_logic;
			C_sync_out	: out	std_logic;
			Blanking_out: out	std_logic;
			dvalid_out	: out	std_logic
		);
	end component;
	
	-- Test bench signals
	signal vclk_tb			: std_logic;
	signal pclk_tb			: std_logic;
	signal Y_tb				: std_logic_vector(7 downto 0);
	signal CbCr_tb			: std_logic_vector(7 downto 0);
	signal is_Cr_tb			: std_logic;
	signal is_odd_tb		: std_logic;
	signal H_sync_tb		: std_logic;
	signal V_sync_tb		: std_logic;
	signal C_sync_tb		: std_logic;
	signal Blanking_tb		: std_logic;
	signal dvalid_tb		: std_logic;
	signal pclk_out_tb		: std_logic;
	signal Y_out_tb			: std_logic_vector(7 downto 0);
	signal Cb_out_tb		: std_logic_vector(7 downto 0);
	signal Cr_out_tb		: std_logic_vector(7 downto 0);
	signal H_sync_out_tb	: std_logic;
	signal V_sync_out_tb	: std_logic;
	signal C_sync_out_tb	: std_logic;
	signal Blanking_out_tb	: std_logic;
	signal dvalid_out_tb	: std_logic;
	
	-- Declare record type to build a test vector for this test bench
	type test_vector is record
		vclk_tb			: std_logic;
		pclk_tb			: std_logic;
		Y_tb			: std_logic_vector(7 downto 0);
		CbCr_tb			: std_logic_vector(7 downto 0);
		is_Cr_tb		: std_logic;
		is_odd_tb		: std_logic;
		H_sync_tb		: std_logic;
		V_sync_tb		: std_logic;
		C_sync_tb		: std_logic;
		Blanking_tb		: std_logic;
		dvalid_tb		: std_logic;
	end record;

	type test_vector_array is array (natural range <>) of test_vector;
	constant test_vectors : test_vector_array := (
		-- vclk	pclk,	Y,		CbCr,	is_Cr,	is_odd,	H_sync,	V_sync,	C_sync,	Blanking,	dvalid
		  ('0',	'0',	x"00",	x"00",	'1',	'0',	'1',	'0',	'0',	'0',		'1'), -- Test normal 4:2:2 to 4:4:4
		  ('1',	'0',	x"00",	x"00",	'1',	'0',	'1',	'0',	'0',	'0',		'1'),
		  ('0',	'1',	x"00",	x"00",	'1',	'0',	'1',	'0',	'0',	'0',		'1'), -- upsampling (with chroma duplication)
		  ('1',	'1',	x"00",	x"00",	'1',	'0',	'1',	'0',	'0',	'0',		'1'),
		  ('0',	'0',	x"01",	x"01",	'0',	'0',	'0',	'1',	'0',	'0',		'1'), -- and test luma and flags correct delay.
		  ('1',	'0',	x"01",	x"01",	'0',	'0',	'0',	'1',	'0',	'0',		'1'),
		  ('0',	'1',	x"01",	x"01",	'0',	'0',	'0',	'1',	'0',	'0',		'1'),
		  ('1',	'1',	x"01",	x"01",	'0',	'0',	'0',	'1',	'0',	'0',		'1'),
		  ('0',	'0',	x"02",	x"02",	'1',	'0',	'0',	'0',	'1',	'0',		'1'),
		  ('1',	'0',	x"02",	x"02",	'1',	'0',	'0',	'0',	'1',	'0',		'1'),
		  ('0',	'1',	x"02",	x"02",	'1',	'0',	'0',	'0',	'1',	'0',		'1'),
		  ('1',	'1',	x"02",	x"02",	'1',	'0',	'0',	'0',	'1',	'0',		'1'),
		  ('0',	'0',	x"04",	x"04",	'0',	'0',	'0',	'0',	'0',	'1',		'1'),
		  ('1',	'0',	x"04",	x"04",	'0',	'0',	'0',	'0',	'0',	'1',		'1'),
		  ('0',	'1',	x"04",	x"04",	'0',	'0',	'0',	'0',	'0',	'1',		'1'),
		  ('1',	'1',	x"04",	x"04",	'0',	'0',	'0',	'0',	'0',	'1',		'1'),
		  ('0',	'0',	x"08",	x"08",	'1',	'0',	'0',	'0',	'0',	'0',		'0'),
		  ('1',	'0',	x"08",	x"08",	'1',	'0',	'0',	'0',	'0',	'0',		'0'),
		  ('0',	'1',	x"08",	x"08",	'1',	'0',	'0',	'0',	'0',	'0',		'0'),
		  ('1',	'1',	x"08",	x"08",	'1',	'0',	'0',	'0',	'0',	'0',		'0'),
		  ('0',	'0',	x"10",	x"10",	'0',	'0',	'0',	'0',	'0',	'1',		'1'),
		  ('1',	'0',	x"10",	x"10",	'0',	'0',	'0',	'0',	'0',	'1',		'1'),
		  ('0',	'1',	x"10",	x"10",	'0',	'0',	'0',	'0',	'0',	'1',		'1'),
		  ('1',	'1',	x"10",	x"10",	'0',	'0',	'0',	'0',	'0',	'1',		'1'),
		  ('0',	'0',	x"20",	x"20",	'1',	'0',	'0',	'0',	'1',	'0',		'1'),
		  ('1',	'0',	x"20",	x"20",	'1',	'0',	'0',	'0',	'1',	'0',		'1'),
		  ('0',	'1',	x"20",	x"20",	'1',	'0',	'0',	'0',	'1',	'0',		'1'),
		  ('1',	'1',	x"20",	x"20",	'1',	'0',	'0',	'0',	'1',	'0',		'1'),
		  ('0',	'0',	x"40",	x"40",	'0',	'0',	'0',	'1',	'0',	'0',		'1'),
		  ('1',	'0',	x"40",	x"40",	'0',	'0',	'0',	'1',	'0',	'0',		'1'),
		  ('0',	'1',	x"40",	x"40",	'0',	'0',	'0',	'1',	'0',	'0',		'1'),
		  ('1',	'1',	x"40",	x"40",	'0',	'0',	'0',	'1',	'0',	'0',		'1'),
		  ('0',	'0',	x"80",	x"80",	'1',	'0',	'1',	'0',	'0',	'0',		'1'),
		  ('1',	'0',	x"80",	x"80",	'1',	'0',	'1',	'0',	'0',	'0',		'1'),
		  ('0',	'1',	x"80",	x"80",	'1',	'0',	'1',	'0',	'0',	'0',		'1'),
		  ('1',	'1',	x"80",	x"80",	'1',	'0',	'1',	'0',	'0',	'0',		'1'),
		  ('0',	'0',	x"81",	x"81",	'0',	'0',	'0',	'0',	'0',	'0',		'1'),
		  ('1',	'0',	x"81",	x"81",	'0',	'0',	'0',	'0',	'0',	'0',		'1'),
		  ('0',	'1',	x"81",	x"81",	'0',	'0',	'0',	'0',	'0',	'0',		'1'),
		  ('1',	'1',	x"81",	x"81",	'0',	'0',	'0',	'0',	'0',	'0',		'1'),
		  
		  ('0',	'0',	x"00",	x"00",	'0',	'0',	'1',	'0',	'0',	'0',		'1'), -- Test change from Cr first
		  ('1',	'0',	x"00",	x"00",	'0',	'0',	'1',	'0',	'0',	'0',		'1'),
		  ('0',	'1',	x"00",	x"00",	'0',	'0',	'1',	'0',	'0',	'0',		'1'), -- to Cb first.
		  ('1',	'1',	x"00",	x"00",	'0',	'0',	'1',	'0',	'0',	'0',		'1'),
		  ('0',	'0',	x"01",	x"01",	'1',	'0',	'0',	'1',	'0',	'0',		'1'),
		  ('1',	'0',	x"01",	x"01",	'1',	'0',	'0',	'1',	'0',	'0',		'1'),
		  ('0',	'1',	x"01",	x"01",	'1',	'0',	'0',	'1',	'0',	'0',		'1'),
		  ('1',	'1',	x"01",	x"01",	'1',	'0',	'0',	'1',	'0',	'0',		'1'),
		  
		  ('0',	'0',	x"02",	x"02",	'0',	'0',	'0',	'0',	'1',	'0',		'1'), -- Test incorrect sequence
		  ('1',	'0',	x"02",	x"02",	'0',	'0',	'0',	'0',	'1',	'0',		'1'),
		  ('0',	'1',	x"02",	x"02",	'0',	'0',	'0',	'0',	'1',	'0',		'1'), -- of chroma samples.
		  ('1',	'1',	x"02",	x"02",	'0',	'0',	'0',	'0',	'1',	'0',		'1'),
		  ('0',	'0',	x"10",	x"10",	'0',	'0',	'1',	'0',	'0',	'0',		'1'),
		  ('1',	'0',	x"10",	x"10",	'0',	'0',	'1',	'0',	'0',	'0',		'1'),
		  ('0',	'1',	x"10",	x"10",	'0',	'0',	'1',	'0',	'0',	'0',		'1'),
		  ('1',	'1',	x"10",	x"10",	'0',	'0',	'1',	'0',	'0',	'0',		'1'),
		  ('0',	'0',	x"20",	x"20",	'1',	'0',	'0',	'1',	'0',	'0',		'1'),
		  ('1',	'0',	x"20",	x"20",	'1',	'0',	'0',	'1',	'0',	'0',		'1'),
		  ('0',	'1',	x"20",	x"20",	'1',	'0',	'0',	'1',	'0',	'0',		'1'),
		  ('1',	'1',	x"20",	x"20",	'1',	'0',	'0',	'1',	'0',	'0',		'1'),
		  ('0',	'0',	x"40",	x"40",	'0',	'0',	'0',	'0',	'1',	'0',		'1'),
		  ('1',	'0',	x"40",	x"40",	'0',	'0',	'0',	'0',	'1',	'0',		'1'),
		  ('0',	'1',	x"40",	x"40",	'0',	'0',	'0',	'0',	'1',	'0',		'1'),
		  ('1',	'1',	x"40",	x"40",	'0',	'0',	'0',	'0',	'1',	'0',		'1'),
		  ('0',	'0',	x"80",	x"80",	'1',	'0',	'0',	'0',	'0',	'1',		'1'),
		  ('1',	'0',	x"80",	x"80",	'1',	'0',	'0',	'0',	'0',	'1',		'1'),
		  ('0',	'1',	x"80",	x"80",	'1',	'0',	'0',	'0',	'0',	'1',		'1'),
		  ('1',	'1',	x"80",	x"80",	'1',	'0',	'0',	'0',	'0',	'1',		'1'),
		  ('0',	'0',	x"00",	x"00",	'0',	'0',	'0',	'0',	'1',	'0',		'1'),
		  ('1',	'0',	x"00",	x"00",	'0',	'0',	'0',	'0',	'1',	'0',		'1'),
		  ('0',	'1',	x"00",	x"00",	'0',	'0',	'0',	'0',	'1',	'0',		'1'),
		  ('1',	'1',	x"00",	x"00",	'0',	'0',	'0',	'0',	'1',	'0',		'1'),
		  ('0',	'0',	x"00",	x"00",	'1',	'0',	'0',	'0',	'0',	'1',		'1'),
		  ('1',	'0',	x"00",	x"00",	'1',	'0',	'0',	'0',	'0',	'1',		'1'),
		  ('0',	'1',	x"00",	x"00",	'1',	'0',	'0',	'0',	'0',	'1',		'1'),
		  ('1',	'1',	x"00",	x"00",	'1',	'0',	'0',	'0',	'0',	'1',		'1')
		);
begin
	uut: component gc_dv_422_to_444 port map (
		vclk			=> vclk_tb,
		pclk			=> pclk_tb,
		Y				=> Y_tb,
		CbCr			=> CbCr_tb,
		is_Cr			=> is_Cr_tb,
		is_odd			=> is_odd_tb,
		H_sync			=> H_sync_tb,
		V_sync			=> V_sync_tb,
		C_sync			=> C_sync_tb,
		Blanking		=> Blanking_tb,
		dvalid			=> dvalid_tb,
		pclk_out		=> pclk_out_tb,
		Y_out			=> Y_out_tb,
		Cb_out			=> Cb_out_tb,
		Cr_out			=> Cr_out_tb,
		H_sync_out		=> H_sync_out_tb,
		V_sync_out		=> V_sync_out_tb,
		C_sync_out		=> C_sync_out_tb,
		Blanking_out	=> Blanking_out_tb,
		dvalid_out		=> dvalid_out_tb
	);
	
	tb1 : process
		constant period: time := 20 ns;
	begin
		for i in test_vectors'range loop
			-- Feed in test data from ith test vector line
			vclk_tb <= test_vectors(i).vclk_tb;
			pclk_tb <= test_vectors(i).pclk_tb;
			Y_tb <= test_vectors(i).Y_tb;
			CbCr_tb <= test_vectors(i).CbCr_tb;
			is_Cr_tb <= test_vectors(i).is_Cr_tb;
			is_odd_tb <= test_vectors(i).is_odd_tb;
			H_sync_tb <= test_vectors(i).H_sync_tb;
			V_sync_tb <= test_vectors(i).V_sync_tb;
			C_sync_tb <= test_vectors(i).C_sync_tb;
			Blanking_tb <= test_vectors(i).Blanking_tb;
			dvalid_tb <= test_vectors(i).dvalid_tb;
			
			wait for period;
		end loop;
		
		wait;
	end process; 
end behav;

HDL/simulation/gc_dv_422_to_444_tb01.vcd
$date
  Tue Mar  9 12:47:49 2021
$end
$version
  GHDL v0
$end
$timescale
  1 fs
$end
$scope module standard $end
$upscope $end
$scope module std_logic_1164 $end
$upscope $end
$scope module numeric_std $end
$upscope $end
$scope module gc_dv_422_to_444_tb $end
$var reg 1 ! vclk_tb $end
$var reg 1 " pclk_tb $end
$var reg 8 # y_tb[7:0] $end
$var reg 8 $ cbcr_tb[7:0] $end
$var reg 1 % is_cr_tb $end
$var reg 1 & is_odd_tb $end
$var reg 1 ' h_sync_tb $end
$var reg 1 ( v_sync_tb $end
$var reg 1 ) c_sync_tb $end
$var reg 1 * blanking_tb $end
$var reg 1 + dvalid_tb $end
$var reg 1 , pclk_out_tb $end
$var reg 8 - y_out_tb[7:0] $end
$var reg 8 . cb_out_tb[7:0] $end
$var reg 8 / cr_out_tb[7:0] $end
$var reg 1 0 h_sync_out_tb $end
$var reg 1 1 v_sync_out_tb $end
$var reg 1 2 c_sync_out_tb $end
$var reg 1 3 blanking_out_tb $end
$var reg 1 4 dvalid_out_tb $end
$scope module uut $end
$var reg 1 5 vclk $end
$var reg 1 6 pclk $end
$var reg 8 7 y[7:0] $end
$var reg 8 8 cbcr[7:0] $end
$var reg 1 9 is_cr $end
$var reg 1 : is_odd $end
$var reg 1 ; h_sync $end
$var reg 1 < v_sync $end
$var reg 1 = c_sync $end
$var reg 1 > blanking $end
$var reg 1 ? dvalid $end
$var reg 1 @ pclk_out $end
$var reg 8 A y_out[7:0] $end
$var reg 8 B cb_out[7:0] $end
$var reg 8 C cr_out[7:0] $end
$var reg 1 D h_sync_out $end
$var reg 1 E v_sync_out $end
$var reg 1 F c_sync_out $end
$var reg 1 G blanking_out $end
$var reg 1 H dvalid_out $end
$var reg 8 I cb_sample[7:0] $end
$var reg 8 J cr_sample[7:0] $end
$var reg 1 K cb_loaded $end
$var reg 1 L cr_loaded $end
$comment y_pipe is not handled $end
$var reg 5 M pclk_pipe[0:4] $end
$var reg 2 N h_sync_pipe[0:1] $end
$var reg 2 O v_sync_pipe[0:1] $end
$var reg 2 P c_sync_pipe[0:1] $end
$var reg 2 Q blanking_pipe[0:1] $end
$var reg 2 R dvalid_pipe[0:1] $end
$upscope $end
$upscope $end
$enddefinitions $end
#0
0!
0"
b00000000 #
b00000000 $
1%
0&
1'
0(
0)
0*
1+
U,
bUUUUUUUU -
bUUUUUUUU .
bUUUUUUUU /
U0
U1
U2
U3
U4
05
06
b00000000 7
b00000000 8
19
0:
1;
0<
0=
0>
1?
U@
bUUUUUUUU A
bUUUUUUUU B
bUUUUUUUU C
UD
UE
UF
UG
UH
bUUUUUUUU I
bUUUUUUUU J
0K
0L
bUUUUU M
bUU N
bUU O
bUU P
bUU Q
bUU R
#20000000
1!
15
b0UUUU M
#40000000
0!
1"
05
16
#60000000
1!
15
b00000000 J
1L
b10UUU M
b1U N
b0U O
b0U P
b0U Q
b1U R
#80000000
0!
0"
b00000001 #
b00000001 $
0%
0'
1(
05
06
b00000001 7
b00000001 8
09
0;
1<
#100000000
1!
15
b010UU M
#120000000
0!
1"
05
16
#140000000
1!
15
b00000001 I
1K
b1010U M
b01 N
b10 O
b00 P
b00 Q
b11 R
#160000000
0!
0"
b00000010 #
b00000010 $
1%
0(
1)
05
06
b00000010 7
b00000010 8
19
0<
1=
#180000000
1!
15
b01010 M
#200000000
0!
1"
05
16
#220000000
1!
0,
b00000000 -
b00000001 .
b00000000 /
10
01
02
03
14
15
0@
b00000000 A
b00000001 B
b00000000 C
1D
0E
0F
0G
1H
b00000010 J
0K
b10101 M
b00 N
b01 O
b10 P
#240000000
0!
0"
b00000100 #
b00000100 $
0%
0)
1*
05
06
b00000100 7
b00000100 8
09
0=
1>
#260000000
1!
1,
15
1@
b01010 M
#280000000
0!
1"
05
16
#300000000
1!
0,
b00000001 -
00
11
15
0@
b00000001 A
0D
1E
b00000100 I
b00000100 J
1K
b10101 M
b00 O
b01 P
b10 Q
#320000000
0!
0"
b00001000 #
b00001000 $
1%
0*
0+
05
06
b00001000 7
b00001000 8
19
0>
0?
#340000000
1!
1,
15
1@
b01010 M
#360000000
0!
1"
05
16
#380000000
1!
0,
b00000010 -
b00000100 .
b00000100 /
01
12
15
0@
b00000010 A
b00000100 B
b00000100 C
0E
1F
b00001000 J
0K
b10101 M
b00 P
b01 Q
b01 R
#400000000
0!
0"
b00010000 #
b00010000 $
0%
1*
1+
05
06
b00010000 7
b00010000 8
09
1>
1?
#420000000
1!
1,
15
1@
b01010 M
#440000000
0!
1"
05
16
#460000000
1!
0,
b00000100 -
02
13
15
0@
b00000100 A
0F
1G
b00010000 I
b00010000 J
1K
b10101 M
b10 Q
b10 R
#480000000
0!
0"
b00100000 #
b00100000 $
1%
1)
0*
05
06
b00100000 7
b00100000 8
19
1=
0>
#500000000
1!
1,
15
1@
b01010 M
#520000000
0!
1"
05
16
#540000000
1!
0,
b00001000 -
b00010000 .
b00010000 /
03
04
15
0@
b00001000 A
b00010000 B
b00010000 C
0G
0H
b00100000 J
0K
b10101 M
b10 P
b01 Q
b11 R
#560000000
0!
0"
b01000000 #
b01000000 $
0%
1(
0)
05
06
b01000000 7
b01000000 8
09
1<
0=
#580000000
1!
1,
15
1@
b01010 M
#600000000
0!
1"
05
16
#620000000
1!
0,
b00010000 -
13
14
15
0@
b00010000 A
1G
1H
b01000000 I
1K
b10101 M
b10 O
b01 P
b00 Q
#640000000
0!
0"
b10000000 #
b10000000 $
1%
1'
0(
05
06
b10000000 7
b10000000 8
19
1;
0<
#660000000
1!
1,
15
1@
b01010 M
#680000000
0!
1"
05
16
#700000000
1!
0,
b00100000 -
b01000000 .
b00100000 /
12
03
15
0@
b00100000 A
b01000000 B
b00100000 C
1F
0G
b10000000 J
0K
b10101 M
b10 N
b01 O
b00 P
#720000000
0!
0"
b10000001 #
b10000001 $
0%
0'
05
06
b10000001 7
b10000001 8
09
0;
#740000000
1!
1,
15
1@
b01010 M
#760000000
0!
1"
05
16
#780000000
1!
0,
b01000000 -
11
02
15
0@
b01000000 A
1E
0F
b10000001 I
1K
b10101 M
b01 N
b00 O
#800000000
0!
0"
b00000000 #
b00000000 $
1'
05
06
b00000000 7
b00000000 8
1;
#820000000
1!
1,
15
1@
b01010 M
#840000000
0!
1"
05
16
#860000000
1!
0,
b10000000 -
b10000001 .
b10000000 /
10
01
15
0@
b10000000 A
b10000001 B
b10000000 C
1D
0E
b00000000 I
0L
b10101 M
b10 N
#880000000
0!
0"
b00000001 #
b00000001 $
1%
0'
1(
05
06
b00000001 7
b00000001 8
19
0;
1<
#900000000
1!
1,
15
1@
b01010 M
#920000000
0!
1"
05
16
#940000000
1!
0,
b10000001 -
00
15
0@
b10000001 A
0D
b00000001 J
1L
b10101 M
b01 N
b10 O
#960000000
0!
0"
b00000010 #
b00000010 $
0%
0(
1)
05
06
b00000010 7
b00000010 8
09
0<
1=
#980000000
1!
1,
15
1@
b01010 M
#1000000000
0!
1"
05
16
#1020000000
1!
0,
b00000000 -
b00000000 .
b00000001 /
10
15
0@
b00000000 A
b00000000 B
b00000001 C
1D
b00000010 I
0L
b10101 M
b00 N
b01 O
b10 P
#1040000000
0!
0"
b00010000 #
b00010000 $
1'
0)
05
06
b00010000 7
b00010000 8
1;
0=
#1060000000
1!
1,
15
1@
b01010 M
#1080000000
0!
1"
05
16
#1100000000
1!
0,
b00000001 -
00
11
15
0@
b00000001 A
0D
1E
b00010000 I
b10101 M
b10 N
b00 O
b01 P
#1120000000
0!
0"
b00100000 #
b00100000 $
1%
0'
1(
05
06
b00100000 7
b00100000 8
19
0;
1<
#1140000000
1!
1,
15
1@
b01010 M
#1160000000
0!
1"
05
16
#1180000000
1!
0,
b00000010 -
01
12
15
0@
b00000010 A
0E
1F
b00100000 J
1L
b10101 M
b01 N
b10 O
b00 P
#1200000000
0!
0"
b01000000 #
b01000000 $
0%
0(
1)
05
06
b01000000 7
b01000000 8
09
0<
1=
#1220000000
1!
1,
15
1@
b01010 M
#1240000000
0!
1"
05
16
#1260000000
1!
0,
b00010000 -
b00010000 .
b00100000 /
10
02
15
0@
b00010000 A
b00010000 B
b00100000 C
1D
0F
b01000000 I
0L
b10101 M
b00 N
b01 O
b10 P
#1280000000
0!
0"
b10000000 #
b10000000 $
1%
0)
1*
05
06
b10000000 7
b10000000 8
19
0=
1>
#1300000000
1!
1,
15
1@
b01010 M
#1320000000
0!
1"
05
16
#1340000000
1!
0,
b00100000 -
00
11
15
0@
b00100000 A
0D
1E
b10000000 I
b10000000 J
1L
b10101 M
b00 O
b01 P
b10 Q
#1360000000
0!
0"
b00000000 #
b00000000 $
0%
1)
0*
05
06
b00000000 7
b00000000 8
09
1=
0>
#1380000000
1!
1,
15
1@
b01010 M
#1400000000
0!
1"
05
16
#1420000000
1!
0,
b01000000 -
b10000000 .
b10000000 /
01
12
15
0@
b01000000 A
b10000000 B
b10000000 C
0E
1F
b00000000 I
0L
b10101 M
b10 P
b01 Q
#1440000000
0!
0"
1%
0)
1*
05
06
19
0=
1>
#1460000000
1!
1,
15
1@
b01010 M
#1480000000
0!
1"
05
16
#1500000000
1!
0,
b10000000 -
02
13
15
0@
b10000000 A
0F
1G
b00000000 J
1L
b10101 M
b01 P
b10 Q
