HDL/GC_Video_Adapter/source/gc_dv_decode.vhd
-- file: gc_dv_decode.vhd

library ieee;
use ieee.std_logic_1164.all;
use ieee.numeric_std.all;

entity gc_dv_decode is
	port(
		vclk	: in	std_logic;
		vphase	: in	std_logic;
		vdata	: in	std_logic_vector(7 downto 0);
		pclk	: out	std_logic := '0';
		Y		: out	std_logic_vector(7 downto 0) := x"10";
		CbCr	: out	std_logic_vector(7 downto 0) := x"80";
		is_Cr	: out	std_logic := '0';
		is_odd	: out	std_logic := '0';
		H_sync	: out	std_logic := '0';
		V_sync	: out	std_logic := '0';
		C_sync	: out	std_logic := '0';
		Blanking: out	std_logic := '0';
		dvalid	: out	std_logic := '0'
	);
end entity;

architecture behav of gc_dv_decode is
	-- vdata buffer
	type vdata_buffer_type is array(0 to 3) of std_logic_vector(7 downto 0);
	signal vdata_buffer			: vdata_buffer_type := (others => x"FF");
	
	-- vphase state signals
	signal last_vphase			: std_logic := '0';
	signal vsample_count		: natural range 0 to 5 := 0;
	
	-- Retain last video mode (<Y0><Y0>... or <Y0>...) for valid data detection
	signal last_vmode			: std_logic := '0'; -- Default '0' is <Y0><Y0>...
	
	signal last_dvalid			: std_logic := '0';

begin
	-- vdata logic
	vdata_process : process(vclk)
		variable valid_sample	: std_logic := '0';
		variable Y_sample		: std_logic_vector(7 downto 0);
		variable CbCr_sample	: std_logic_vector(7 downto 0);

	begin
		if (rising_edge(vclk)) then
			-- 
			if (last_dvalid = '1') then
				-- 
				if (((vsample_count = 4) and (last_vmode = '0')) or ((vsample_count = 2) and (last_vmode = '1'))) then
					pclk <= '0';
				end if;
				-- 
				if (((vsample_count = 2) and (last_vmode = '0')) or ((vsample_count = 1) and (last_vmode = '1'))) then
					pclk <= '1';
				end if;
			end if;
			
			-- Store new vdata sample and shift samples
			vdata_buffer <= vdata & vdata_buffer(0 to 2);
			
			-- Increment number of vdata samples taken on vclk
			if (vsample_count < 4) then
				vsample_count <= vsample_count + 1;
			end if;
			
			-- Set defaults for the case that no valid samples is processed.
			if ((vsample_count = 4) or ((vsample_count = 2) and (last_vmode = '1'))) then
				Y <= x"10";
				CbCr <= x"80";
				is_Cr <= '0';
				is_odd <= '0';
				H_sync <= '0';
				V_sync <= '0';
				C_sync <= '0';
				Blanking <= '0';
				dvalid <= '0';
				last_dvalid <= '0';
			end if;
			
			-- Update previous vphase state for comparison
			last_vphase <= vphase;
			
			-- Process new video sample using vphase as trigger
			if (vphase /= last_vphase) then
				vsample_count <= 1; -- Set sample counter to 1 (current sample) after vphase change
			
				-- Get Y and CbCr sample depending on the vdata stream format
				if (vsample_count = 2) then		-- vdata: <Y0><CbCr0><Y1><CbCr1>...
					last_vmode <= '1';
					valid_sample := '1';
					Y_sample := vdata_buffer(1);
					CbCr_sample := vdata_buffer(0);
				elsif (vsample_count = 4) then	-- vdata: <Y0><Y0><CbCr0><CbCr0><Y1><Y1><CbCr1><CbCr1>...
					last_vmode <= '0';
					valid_sample := '1';
					Y_sample := vdata_buffer(3);
					CbCr_sample := vdata_buffer(1);
				end if;	-- if (vsample_count = 2)
			end if;	-- if (vphase /= last_vphase)
			
			-- If new sample exists, set output interface video values and flags
			if (valid_sample = '1') then
				valid_sample := '0';
				dvalid <= '1';
				last_dvalid <= '1';
				
				if (Y_sample = x"00") then	-- blanking data
					Y <= x"10";
					CbCr <= x"80";
					H_sync <= not CbCr_sample(4);	-- Active low.
					V_sync <= not CbCr_sample(5);	-- Active low.
					is_odd <= not CbCr_sample(6);	-- Active low.
					C_sync <= not CbCr_sample(7);	-- Active low.
					Blanking <= '1';
					is_Cr <= '0';
				else						-- video sample
					Y <= Y_sample;
					CbCr <= CbCr_sample;
					H_sync <= '0';
					V_sync <= '0';
					is_odd <= '0';
					C_sync <= '0';
					Blanking <= '0';
					
					if (last_vphase = '1') then
						is_Cr <= '1';
					else
						is_Cr <= '0';
					end if;	-- if (vphase = '1')
				end if;	-- if (Y_sample = x"00")
			end if;	-- if (valid_sample = '1')
		end if;	-- if (rising_edge(vclk))
	end process;
end behav;

HDL/GC_Video_Adapter/source/gc_dv_decode_tb.vhd
-- file: gc_dv_decode_tb.vhd

library ieee;
use ieee.std_logic_1164.all;
use ieee.numeric_std.all;

entity gc_dv_decode_tb is
end entity;

architecture behav of gc_dv_decode_tb is

	component gc_dv_decode is
		port(
			vclk	: in	std_logic;
			vphase	: in	std_logic;
			vdata	: in	std_logic_vector(7 downto 0);
			pclk	: out	std_logic;
			Y		: out	std_logic_vector(7 downto 0);
			CbCr	: out	std_logic_vector(7 downto 0);
			is_Cr	: out	std_logic;
			is_odd	: out	std_logic;
			H_sync	: out	std_logic;
			V_sync	: out	std_logic;
			C_sync	: out	std_logic;
			Blanking: out	std_logic;
			dvalid	: out	std_logic
		);
	end component;
	
	-- Test bench signals
	signal vclk_tb		: std_logic;
	signal vphase_tb	: std_logic;
	signal vdata_tb		: std_logic_vector(7 downto 0);
	signal pclk_tb		: std_logic;
	signal Y_tb			: std_logic_vector(7 downto 0);
	signal CbCr_tb		: std_logic_vector(7 downto 0);
	signal is_Cr_tb		: std_logic;
	signal is_odd_tb	: std_logic;
	signal H_sync_tb	: std_logic;
	signal V_sync_tb	: std_logic;
	signal C_sync_tb	: std_logic;
	signal Blanking_tb	: std_logic;
	signal dvalid_tb	: std_logic;
	
	-- Declare record type to build a test vector for this test bench
	type test_vector is record
			vclk_tb		: std_logic;
			vphase_tb	: std_logic;
			vdata_tb	: std_logic_vector(7 downto 0);
	end record;

	type test_vector_array is array (natural range <>) of test_vector;
	constant test_vectors : test_vector_array := (
		-- vclk, vphase, vdata
		  ('0',  '0',    x"00"),	-- fast data, blanking data, raw flags low
		  ('1',  '0',    x"00"),
		  ('0',  '0',    x"00"),
		  ('1',  '0',    x"00"),
		  ('0',  '0',    x"00"),
		  ('1',  '0',    x"00"),
		  
		  ('0',  '1',    x"00"),	-- fast data, blanking data, raw flag bit 4 high
		  ('1',  '1',    x"00"),
		  ('0',  '1',    x"10"),
		  ('1',  '1',    x"10"),
		  
		  ('0',  '0',    x"00"),	-- fast data, blanking data, raw flag bit 5 high
		  ('1',  '0',    x"00"),
		  ('0',  '0',    x"20"),
		  ('1',  '0',    x"20"),
		  
		  ('0',  '1',    x"00"),	-- fast data, blanking data, raw flag bit 7 high
		  ('1',  '1',    x"00"),
		  ('0',  '1',    x"80"),
		  ('1',  '1',    x"80"),
		  
		  ('0',  '0',    x"00"),	-- fast data, color data
		  ('1',  '0',    x"00"),
		  ('0',  '0',    x"00"),
		  ('1',  '0',    x"00"),
		  
		  ('0',  '1',    x"01"),
		  ('1',  '1',    x"01"),
		  ('0',  '1',    x"01"),
		  ('1',  '1',    x"01"),
		  
		  ('0',  '0',    x"02"),
		  ('1',  '0',    x"02"),
		  ('0',  '0',    x"02"),
		  ('1',  '0',    x"02"),
		  
		  ('0',  '1',    x"04"),
		  ('1',  '1',    x"04"),
		  ('0',  '1',    x"04"),
		  ('1',  '1',    x"04"),
		  
		  ('0',  '0',    x"08"),
		  ('1',  '0',    x"08"),
		  ('0',  '0',    x"08"),
		  ('1',  '0',    x"08"),
		  
		  ('0',  '1',    x"10"),
		  ('1',  '1',    x"10"),
		  ('0',  '1',    x"10"),
		  ('1',  '1',    x"10"),
		  
		  ('0',  '1',    x"20"),
		  ('1',  '1',    x"20"),
		  ('0',  '1',    x"20"),
		  ('1',  '1',    x"20"),
		  
		  ('0',  '1',    x"40"),
		  ('1',  '1',    x"40"),
		  ('0',  '1',    x"40"),
		  ('1',  '1',    x"40"),
		  
		  ('0',  '1',    x"80"),
		  ('1',  '1',    x"80"),
		  ('0',  '1',    x"80"),
		  ('1',  '1',    x"80"),
		  
		  ('0',  '0',    x"00"),
		  ('1',  '0',    x"00"),
		  ('0',  '0',    x"00"),
		  ('1',  '0',    x"00"),
		  
		  ('0',  '1',    x"00"),
		  ('1',  '1',    x"00"),
		  ('0',  '1',    x"00"),
		  ('1',  '1',    x"00")
		);
begin
	
	uut: component gc_dv_decode port map (
		vclk		=> vclk_tb,
		vphase		=> vphase_tb,
		vdata		=> vdata_tb,
		pclk		=> pclk_tb,
		Y			=> Y_tb,
		CbCr		=> CbCr_tb,
		is_Cr		=> is_Cr_tb,
		is_odd		=> is_odd_tb,
		H_sync		=> H_sync_tb,
		V_sync		=> V_sync_tb,
		C_sync		=> C_sync_tb,
		Blanking	=> Blanking_tb,
		dvalid		=> dvalid_tb
	);
	
	tb1 : process
		constant period: time := 20 ns;
	begin
		for i in test_vectors'range loop
			-- Feed in test data from ith test vector line
			vclk_tb <= test_vectors(i).vclk_tb;
			vphase_tb <= test_vectors(i).vphase_tb;
			vdata_tb <= test_vectors(i).vdata_tb;

			wait for period;
		end loop;
		
		wait;
	end process;
end behav;

HDL/GC_Video_Adapter/source/gc_dv_decode_tb03.vcd
$date
  Sat Feb 27 16:58:06 2021
$end
$version
  GHDL v0
$end
$timescale
  1 fs
$end
$scope module standard $end
$upscope $end
$scope module std_logic_1164 $end
$upscope $end
$scope module numeric_std $end
$upscope $end
$scope module gc_dv_decode_tb $end
$var reg 1 ! vclk_tb $end
$var reg 1 " vphase_tb $end
$var reg 8 # vdata_tb[7:0] $end
$var reg 1 $ pclk_tb $end
$var reg 8 % y_tb[7:0] $end
$var reg 8 & cbcr_tb[7:0] $end
$var reg 1 ' is_cr_tb $end
$var reg 1 ( is_odd_tb $end
$var reg 1 ) h_sync_tb $end
$var reg 1 * v_sync_tb $end
$var reg 1 + c_sync_tb $end
$var reg 1 , blanking_tb $end
$var reg 1 - dvalid_tb $end
$scope module uut $end
$var reg 1 . vclk $end
$var reg 1 / vphase $end
$var reg 8 0 vdata[7:0] $end
$var reg 1 1 pclk $end
$var reg 8 2 y[7:0] $end
$var reg 8 3 cbcr[7:0] $end
$var reg 1 4 is_cr $end
$var reg 1 5 is_odd $end
$var reg 1 6 h_sync $end
$var reg 1 7 v_sync $end
$var reg 1 8 c_sync $end
$var reg 1 9 blanking $end
$var reg 1 : dvalid $end
$comment vdata_buffer is not handled $end
$var reg 1 ; last_vphase $end
$var integer 32 < vsample_count $end
$var reg 1 = last_vmode $end
$var reg 1 > last_dvalid $end
$upscope $end
$upscope $end
$enddefinitions $end
#0
0!
0"
b00000000 #
0$
b00010000 %
b10000000 &
0'
0(
0)
0*
0+
0,
0-
0.
0/
b00000000 0
01
b00010000 2
b10000000 3
04
05
06
07
08
09
0:
0;
b0 <
0=
0>
#20000000
1!
1.
b1 <
#40000000
0!
0.
#60000000
1!
1.
b10 <
#80000000
0!
0.
#100000000
1!
1.
b11 <
#120000000
0!
0.
#140000000
1!
1.
b100 <
#160000000
0!
1"
0.
1/
#180000000
1!
1(
1)
1*
1+
1,
1-
1.
15
16
17
18
19
1:
1;
b1 <
1>
#200000000
0!
b11101111 #
0.
b11101111 0
#220000000
1!
1.
b10 <
#240000000
0!
0"
b00000000 #
0.
0/
b00000000 0
#260000000
1!
1$
0(
0*
0+
1.
11
05
07
08
0;
b1 <
1=
#280000000
0!
0.
#300000000
1!
1.
b10 <
#320000000
0!
b11011111 #
0.
b11011111 0
#340000000
1!
0$
1.
01
b11 <
#360000000
0!
0.
#380000000
1!
1.
b100 <
#400000000
0!
1"
b00000000 #
0.
1/
b00000000 0
#420000000
1!
0)
1*
1.
06
17
19
1:
1;
b1 <
0=
#440000000
0!
b01111111 #
0.
b01111111 0
#460000000
1!
1.
b10 <
#480000000
0!
0"
b00000000 #
0.
0/
b00000000 0
#500000000
1!
1$
0*
1+
1.
11
07
18
0;
b1 <
1=
#520000000
0!
0.
#540000000
1!
1.
b10 <
#560000000
0!
b11111111 #
0.
b11111111 0
#580000000
1!
0$
1.
01
b11 <
#600000000
0!
0.
#620000000
1!
1.
b100 <
#640000000
0!
1"
b00000001 #
0.
1/
b00000001 0
#660000000
1!
0+
1.
08
19
1:
1;
b1 <
0=
#680000000
0!
0.
#700000000
1!
1.
b10 <
#720000000
0!
0"
b00000010 #
0.
0/
b00000010 0
#740000000
1!
1$
b00000001 %
b00000001 &
1'
0,
1.
11
b00000001 2
b00000001 3
14
09
0;
b1 <
1=
#760000000
0!
0.
#780000000
1!
1.
b10 <
#800000000
0!
0.
#820000000
1!
0$
1.
01
b11 <
#840000000
0!
0.
#860000000
1!
1.
b100 <
#880000000
0!
1"
b00000100 #
0.
1/
b00000100 0
#900000000
1!
b00000010 %
b00000010 &
0'
1.
b00000010 2
b00000010 3
04
1:
1;
b1 <
0=
#920000000
0!
0.
#940000000
1!
1.
b10 <
#960000000
0!
0"
b00001000 #
0.
0/
b00001000 0
#980000000
1!
1$
b00000100 %
b00000100 &
1'
1.
11
b00000100 2
b00000100 3
14
0;
b1 <
1=
#1000000000
0!
0.
#1020000000
1!
1.
b10 <
#1040000000
0!
0.
#1060000000
1!
0$
1.
01
b11 <
#1080000000
0!
0.
#1100000000
1!
1.
b100 <
#1120000000
0!
1"
b00010000 #
0.
1/
b00010000 0
#1140000000
1!
b00001000 %
b00001000 &
0'
1.
b00001000 2
b00001000 3
04
1:
1;
b1 <
0=
#1160000000
0!
0.
#1180000000
1!
1.
b10 <
#1200000000
0!
0"
b00100000 #
0.
0/
b00100000 0
#1220000000
1!
1$
b00010000 %
b00010000 &
1'
1.
11
b00010000 2
b00010000 3
14
0;
b1 <
1=
#1240000000
0!
0.
#1260000000
1!
1.
b10 <
#1280000000
0!
0.
#1300000000
1!
0$
1.
01
b11 <
#1320000000
0!
0.
#1340000000
1!
1.
b100 <
#1360000000
0!
1"
b01000000 #
0.
1/
b01000000 0
#1380000000
1!
b00100000 %
b00100000 &
0'
1.
b00100000 2
b00100000 3
04
1:
1;
b1 <
0=
#1400000000
0!
0.
#1420000000
1!
1.
b10 <
#1440000000
0!
0"
b10000000 #
0.
0/
b10000000 0
#1460000000
1!
1$
b01000000 %
b01000000 &
1'
1.
11
b01000000 2
b01000000 3
14
0;
b1 <
1=
#1480000000
0!
0.
#1500000000
1!
1.
b10 <
#1520000000
0!
0.
#1540000000
1!
0$
1.
01
b11 <
#1560000000
0!
0.
#1580000000
1!
1.
b100 <
#1600000000
0!
1"
b00000000 #
0.
1/
b00000000 0
#1620000000
1!
b10000000 %
b10000000 &
0'
1.
b10000000 2
b10000000 3
04
1:
1;
b1 <
0=
#1640000000
0!
0.
#1660000000
1!
1.
b10 <
#1680000000
0!
0"
0.
0/
#1700000000
1!
1$
b00010000 %
1(
1)
1*
1+
1,
1.
11
b00010000 2
15
16
17
18
19
0;
b1 <
1=
#1720000000
0!
0.
#1740000000
1!
1.
b10 <
#1760000000
0!
0.
#1780000000
1!
0$
1.
01
b11 <
#1800000000
0!
0.
#1820000000
1!
1.
b100 <
